gpu_active/__init__.py
gpu_active/gpu_active.py
gpu_active-0.1.1.dist-info/LICENSE
gpu_active-0.1.1.dist-info/METADATA
gpu_active-0.1.1.dist-info/WHEEL
gpu_active-0.1.1.dist-info/top_level.txt
gpu_active-0.1.1.dist-info/RECORD
