Metadata-Version: 2.1
Name: gpu-active
Version: 0.1.1
Summary: Utilities for GPU activation and data transfer in PyTorch.
Home-page: https://github.com/dimeneman/get-gpu
Author: Eman Gope
Author-email: gopeeman87@gmail.com
Classifier: Programming Language :: Python :: 3
Classifier: License :: OSI Approved :: MIT License
Classifier: Operating System :: OS Independent
Requires-Python: >=3.7
License-File: LICENSE
Requires-Dist: torch>=1.7.0
